wordfrequencer/__init__.py
wordfrequencer/wordfrequencer.py
wordfrequencer-0.1.0.dist-info/License
wordfrequencer-0.1.0.dist-info/METADATA
wordfrequencer-0.1.0.dist-info/WHEEL
wordfrequencer-0.1.0.dist-info/top_level.txt
wordfrequencer-0.1.0.dist-info/RECORD
