Metadata-Version: 2.1
Name: wordfrequencer
Version: 0.1.0
Summary: A package to count word frequency and display it in a table format.
Author: Md. Ismiel Hossen Abir
Author-email: ismielabir1971@gmail.com
Classifier: Programming Language :: Python :: 3
Classifier: License :: OSI Approved :: MIT License
Classifier: Operating System :: OS Independent
Requires-Python: >=3.6
License-File: License
